setup.py
DSND_distributions_practice/Binomialdistribution.py
DSND_distributions_practice/Gaussiandistribution.py
DSND_distributions_practice/Generaldistribution.py
DSND_distributions_practice/__init__.py
DSND_distributions_practice.egg-info/PKG-INFO
DSND_distributions_practice.egg-info/SOURCES.txt
DSND_distributions_practice.egg-info/dependency_links.txt
DSND_distributions_practice.egg-info/not-zip-safe
DSND_distributions_practice.egg-info/top_level.txt