Metadata-Version: 1.0
Name: DSND-distributions-practice
Version: 0.1
Summary: Gaussian and Binomial distributions
Home-page: UNKNOWN
Author: Francisco Patino
Author-email: UNKNOWN
License: UNKNOWN
Platform: UNKNOWN
